LICENSE
MANIFEST.in
README
README.md
setup.cfg
setup.py
pyiArduinoI2Cjoystick/__init__.py
pyiArduinoI2Cjoystick/iarduino_I2C_Joystick.cpp
pyiArduinoI2Cjoystick/iarduino_I2C_Joystick.h
pyiArduinoI2Cjoystick/iarduino_I2C_Joystick.pxd
pyiArduinoI2Cjoystick/iarduino_I2C_PI.cpp
pyiArduinoI2Cjoystick/iarduino_I2C_PI.h
pyiArduinoI2Cjoystick/pyiArduinoI2Cjoystick.cpp
pyiArduinoI2Cjoystick/pyiArduinoI2Cjoystick.pyx
pyiArduinoI2Cjoystick/setup.py
pyiArduinoI2Cjoystick.egg-info/PKG-INFO
pyiArduinoI2Cjoystick.egg-info/SOURCES.txt
pyiArduinoI2Cjoystick.egg-info/dependency_links.txt
pyiArduinoI2Cjoystick.egg-info/top_level.txt
pyiArduinoI2Cjoystick/cpp/Calibration.cpp
pyiArduinoI2Cjoystick/cpp/CalibrationManual.cpp
pyiArduinoI2Cjoystick/cpp/ChangeAxisDir.cpp
pyiArduinoI2Cjoystick/cpp/FindDevices.cpp
pyiArduinoI2Cjoystick/cpp/GetADC.cpp
pyiArduinoI2Cjoystick/cpp/GetDirection.cpp
pyiArduinoI2Cjoystick/cpp/GetPosition.cpp
pyiArduinoI2Cjoystick/cpp/NewAddress.cpp
pyiArduinoI2Cjoystick/cpp/Includes/WString.cpp
pyiArduinoI2Cjoystick/cpp/Includes/WString.h
pyiArduinoI2Cjoystick/cpp/Includes/dtostrf.cpp
pyiArduinoI2Cjoystick/cpp/Includes/dtostrf.h
pyiArduinoI2Cjoystick/cpp/Includes/itoa.cpp
pyiArduinoI2Cjoystick/cpp/Includes/itoa.h
pyiArduinoI2Cjoystick/examples/Calibration.py
pyiArduinoI2Cjoystick/examples/CalibrationManual.py
pyiArduinoI2Cjoystick/examples/ChangeAxisDir.py
pyiArduinoI2Cjoystick/examples/FindDevices.py
pyiArduinoI2Cjoystick/examples/GetADC.py
pyiArduinoI2Cjoystick/examples/GetDirection.py
pyiArduinoI2Cjoystick/examples/GetPosition.py
pyiArduinoI2Cjoystick/examples/newAddress.py